atsphinx/pythontutor/__init__.py
atsphinx/pythontutor/directives.py
atsphinx/pythontutor/nodes.py
atsphinx/pythontutor/writers.py
atsphinx_pythontutor-0.2.0.dist-info/METADATA
atsphinx_pythontutor-0.2.0.dist-info/WHEEL
atsphinx_pythontutor-0.2.0.dist-info/licenses/LICENSE
atsphinx_pythontutor-0.2.0.dist-info/RECORD
